docstring_gen_ollama/__about__.py
docstring_gen_ollama/__init__.py
docstring_gen_ollama/docstring_generator.py
docstring_gen_ollama-0.1.3.dist-info/METADATA
docstring_gen_ollama-0.1.3.dist-info/WHEEL
docstring_gen_ollama-0.1.3.dist-info/entry_points.txt
docstring_gen_ollama-0.1.3.dist-info/licenses/LICENSE.txt
docstring_gen_ollama-0.1.3.dist-info/RECORD
