Metadata-Version: 2.3
Name: docstring-gen-ollama
Version: 0.1.3
Summary: generate python docstrings using ollama
Project-URL: Documentation, https://github.com/cpossinger/docstring-gen-ollama#readme
Project-URL: Issues, https://github.com/cpossinger/docstring-gen-ollama/issues
Project-URL: Source, https://github.com/cpossinger/docstring-gen-ollama
Author: cam
License-Expression: MIT
License-File: LICENSE.txt
Classifier: Development Status :: 4 - Beta
Classifier: Programming Language :: Python
Classifier: Programming Language :: Python :: 3.8
Classifier: Programming Language :: Python :: 3.9
Classifier: Programming Language :: Python :: 3.10
Classifier: Programming Language :: Python :: 3.11
Classifier: Programming Language :: Python :: 3.12
Classifier: Programming Language :: Python :: Implementation :: CPython
Classifier: Programming Language :: Python :: Implementation :: PyPy
Requires-Python: >=3.8
Requires-Dist: ollama
Requires-Dist: tqdm
